pyecotrend_ista/__init__.py
pyecotrend_ista/__version.py
pyecotrend_ista/const.py
pyecotrend_ista/exception_classes.py
pyecotrend_ista/helper_object_de.py
pyecotrend_ista/login_helper.py
pyecotrend_ista/pyecotrend_ista.py
pyecotrend_ista/types.py
pyecotrend_ista/ua.json
pyecotrend_ista-3.3.3.dist-info/licenses/LICENSE
pyecotrend_ista-3.3.3.dist-info/METADATA
pyecotrend_ista-3.3.3.dist-info/WHEEL
pyecotrend_ista-3.3.3.dist-info/top_level.txt
pyecotrend_ista-3.3.3.dist-info/RECORD
